[
    {
        "data": [
            {
                "allowSdrSoftwareBrightness": false,
                "autoRotation": "InTabletMode",
                "brightness": 1,
                "colorProfileSource": "sRGB",
                "connectorName": "eDP-1",
                "edidHash": "be7b112de29136ea2111f8dfced92312",
                "edidIdentifier": "CMN 5409 0 1 2020 0",
                "highDynamicRange": false,
                "iccProfilePath": "",
                "mode": {
                    "height": 1080,
                    "refreshRate": 144003,
                    "width": 1920
                },
                "overscan": 0,
                "rgbRange": "Automatic",
                "scale": 1.25,
                "sdrBrightness": 200,
                "sdrGamutWideness": 0,
                "transform": "Normal",
                "vrrPolicy": "Automatic",
                "wideColorGamut": false
            },
            {
                "allowSdrSoftwareBrightness": false,
                "autoRotation": "InTabletMode",
                "brightness": 0.71,
                "colorProfileSource": "sRGB",
                "connectorName": "HDMI-A-1",
                "edidHash": "f003fe6769b848cd2ea7b98d8e209098",
                "edidIdentifier": "AOC 9217 42 1 2021 0",
                "highDynamicRange": false,
                "iccProfilePath": "",
                "mode": {
                    "height": 1080,
                    "refreshRate": 144001,
                    "width": 1920
                },
                "overscan": 0,
                "rgbRange": "Automatic",
                "scale": 1,
                "sdrBrightness": 200,
                "sdrGamutWideness": 0,
                "transform": "Normal",
                "vrrPolicy": "Automatic",
                "wideColorGamut": false
            }
        ],
        "name": "outputs"
    },
    {
        "data": [
            {
                "lidClosed": false,
                "outputs": [
                    {
                        "enabled": true,
                        "outputIndex": 0,
                        "position": {
                            "x": 1920,
                            "y": 0
                        },
                        "priority": 1
                    },
                    {
                        "enabled": true,
                        "outputIndex": 1,
                        "position": {
                            "x": 0,
                            "y": 0
                        },
                        "priority": 0
                    }
                ]
            },
            {
                "lidClosed": false,
                "outputs": [
                    {
                        "enabled": true,
                        "outputIndex": 0,
                        "position": {
                            "x": 0,
                            "y": 0
                        },
                        "priority": 0
                    }
                ]
            }
        ],
        "name": "setups"
    }
]
